tempo120.py
gfx/car.png
gfx/screenshot1.png
gfx/screenshot2.png
gfx/screenshot3.png
gfx/screenshot4.png
gfx/title.png
gfx/track01.png
muzak/engine.ogg
muzak/track.ogg
scores/scores.txt
tempo120-1.8.0.dist-info/LICENSE
tempo120-1.8.0.dist-info/METADATA
tempo120-1.8.0.dist-info/WHEEL
tempo120-1.8.0.dist-info/entry_points.txt
tempo120-1.8.0.dist-info/top_level.txt
tempo120-1.8.0.dist-info/RECORD
