Metadata-Version: 2.1
Name: tempo120
Version: 1.8.0
Summary: A party car racing game
Home-page: https://github.com/dkrajzew/tempo120
Download-URL: http://pypi.python.org/pypi/tempo120
Author: dkrajzew
Author-email: d.krajzewicz@gmail.com
License: GPLv3
Project-URL: Source, https://github.com/dkrajzew/tempo120
Project-URL: Tracker, https://github.com/dkrajzew/tempo120/issues
Project-URL: Discussions, https://github.com/dkrajzew/tempo120/discussions
Classifier: Development Status :: 5 - Production/Stable
Classifier: Programming Language :: Python
Classifier: Programming Language :: Python :: 3
Classifier: License :: OSI Approved :: GNU General Public License v3 (GPLv3)
Classifier: Operating System :: OS Independent
Classifier: Intended Audience :: End Users/Desktop
Classifier: Topic :: Games/Entertainment
Requires-Python: >=2.7, <4
License-File: LICENSE
Requires-Dist: pygame ==2.6.0
